orangebeard_robotframework/__init__.py
orangebeard_robotframework/listener.py
orangebeard_robotframework-2.18.0.dist-info/licenses/LICENSE
orangebeard_robotframework-2.18.0.dist-info/METADATA
orangebeard_robotframework-2.18.0.dist-info/WHEEL
orangebeard_robotframework-2.18.0.dist-info/top_level.txt
orangebeard_robotframework-2.18.0.dist-info/RECORD
