Metadata-Version: 2.4
Name: orangebeard-robotframework
Version: 2.18.0
Summary: A robotframework listener for Orangebeard
Author-email: Tom Heintzberger <tom@orangebeard.io>
License-Expression: AGPL-3.0-or-later
Project-URL: Homepage, https://github.com/orangebeard-io/robotframework-listener
Project-URL: Bug Tracker, https://github.com/orangebeard-io/robotframework-listener/issues
Classifier: Programming Language :: Python :: 3
Classifier: Operating System :: OS Independent
Requires-Python: >=3.7
License-File: LICENSE
Requires-Dist: robotframework>=6.1.1
Requires-Dist: orangebeard-client>=2.7.2
Dynamic: license-file
